abdttsslug/__init__.py
abdttsslug/abdttsslug.py
abdttsslug/cli.py
abdttsslug-0.0.3.dist-info/LICENSE
abdttsslug-0.0.3.dist-info/METADATA
abdttsslug-0.0.3.dist-info/WHEEL
abdttsslug-0.0.3.dist-info/entry_points.txt
abdttsslug-0.0.3.dist-info/top_level.txt
abdttsslug-0.0.3.dist-info/RECORD
