Metadata-Version: 2.1
Name: abdttsslug
Version: 0.0.3
Summary: Sum of square
Home-page: https://github.com/tatlisumak/abdttsslug
Author: Abdullah Tatlısumak
Author-email: matatlisumak@gmail.com
License: MIT license
Keywords: abdttsslug
Platform: UNKNOWN
Classifier: Development Status :: 2 - Pre-Alpha
Classifier: Intended Audience :: Developers
Classifier: License :: OSI Approved :: MIT License
Classifier: Natural Language :: English
Classifier: Programming Language :: Python :: 3
Classifier: Programming Language :: Python :: 3.5
Classifier: Programming Language :: Python :: 3.6
Classifier: Programming Language :: Python :: 3.7
Classifier: Programming Language :: Python :: 3.8
Requires-Python: >=3.5
Requires-Dist: Click (>=7.0)
